README.rst
setup.py
ejemplos/__init__.py
libredte/__init__.py
libredte.api_client.egg-info/PKG-INFO
libredte.api_client.egg-info/SOURCES.txt
libredte.api_client.egg-info/dependency_links.txt
libredte.api_client.egg-info/requires.txt
libredte.api_client.egg-info/top_level.txt
libredte/api_client/__init__.py
libredte/api_client/base.py
libredte/api_client/client.py
libredte/api_client/exceptions.py
libredte/api_client/sii/__init__.py
libredte/api_client/sii/actividades_economicas.py
libredte/api_client/sii/bhe.py
libredte/api_client/sii/bte.py
libredte/api_client/sii/contribuyentes.py
libredte/api_client/sii/dte.py
libredte/api_client/sii/indicadores.py
libredte/api_client/sii/portal_mipyme.py
libredte/api_client/sii/rcv.py
libredte/api_client/sii/respaldo_sii.py