Metadata-Version: 1.1
Name: libredte.api-client
Version: 2.5.0
Summary: Cliente para realizar la integración con los servicios web de la API de LibreDTE desde Python
Home-page: https://github.com/LibreDTE/libredte-api-client-python
Author: Esteban De La Fuente Rubio, DeLaF
Author-email: esteban@sasco.cl
License: LGPL
Keywords: facturación electrónica
Platform: UNKNOWN
Classifier: Development Status :: 5 - Production/Stable
Classifier: Intended Audience :: Developers
Classifier: Topic :: Software Development :: Build Tools
Classifier: License :: OSI Approved :: GNU Lesser General Public License v3 or later (LGPLv3+)
Classifier: Programming Language :: Python :: 3
